nocp/__init__.py
nocp/__main__.py
nocp/locales/de/LC_MESSAGES/messages.mo
nocp/locales/en/LC_MESSAGES/messages.mo
nocp/locales/es/LC_MESSAGES/messages.mo
nocp/locales/fr/LC_MESSAGES/messages.mo
nocp/locales/it/LC_MESSAGES/messages.mo
nocp/locales/pt/LC_MESSAGES/messages.mo
nocp-0.2.2.dist-info/METADATA
nocp-0.2.2.dist-info/WHEEL
nocp-0.2.2.dist-info/entry_points.txt
nocp-0.2.2.dist-info/top_level.txt
nocp-0.2.2.dist-info/RECORD
