Metadata-Version: 2.4
Name: nocp
Version: 0.2.2
Summary: Navidrome On Console Player
Author-email: fraoustin <fraoustin@gmail.com>
License-Expression: MIT AND (Apache-2.0 OR BSD-2-Clause)
Project-URL: Homepage, https://github.com/fraoustin/nocp
Project-URL: Repository, https://github.com/fraoustin/nocp
Project-URL: Issues, https://github.com/fraoustin/nocp/issues
Requires-Python: >=3.7
Requires-Dist: python-vlc
Requires-Dist: urwid
Requires-Dist: click
Requires-Dist: requests
